wagtail_link_block/__init__.py
wagtail_link_block/blocks.py
wagtail_link_block/locale/fr/LC_MESSAGES/django.mo
wagtail_link_block/locale/fr/LC_MESSAGES/django.po
wagtail_link_block/static/link_block/link_block.css
wagtail_link_block/static/link_block/link_block.js
wagtail_link_block/templates/wagtailadmin/block_forms/link_block.html
wagtail_link_block/wagtail_hooks.py
wagtail_link_block-1.1.7.dist-info/LICENSE
wagtail_link_block-1.1.7.dist-info/METADATA
wagtail_link_block-1.1.7.dist-info/WHEEL
wagtail_link_block-1.1.7.dist-info/RECORD
